data_pipeline_helper/__init__.py
data_pipeline_helper/cleaning.py
data_pipeline_helper/etl.py
data_pipeline_helper/sql_builder.py
data_pipeline_helper_vi-2.1.0.dist-info/licenses/LICENSE
tests/__init__.py
tests/test_cleaning.py
tests/test_etl.py
tests/test_sql_builder.py
data_pipeline_helper_vi-2.1.0.dist-info/METADATA
data_pipeline_helper_vi-2.1.0.dist-info/WHEEL
data_pipeline_helper_vi-2.1.0.dist-info/top_level.txt
data_pipeline_helper_vi-2.1.0.dist-info/RECORD
